newscrawler/__init__.py
newscrawler/__version__.py
newscrawler/crawler.py
newscrawler/extract_rss.py
newscrawler/utils.py
NewsCrawler3-0.1.9.dist-info/LICENSE
NewsCrawler3-0.1.9.dist-info/METADATA
NewsCrawler3-0.1.9.dist-info/WHEEL
NewsCrawler3-0.1.9.dist-info/top_level.txt
NewsCrawler3-0.1.9.dist-info/RECORD
