Metadata-Version: 2.1
Name: NewsCrawler3
Version: 0.1.9
Summary: NewsCrawler - a library to crawl online newspaper articles
Home-page: https://github.com/NewsPipe/NewsCrawler
Author: Steven Mi
Author-email: s0558366@htw-berlin.de
License: Apache 2.0
Keywords: newspaper article crawler
Platform: UNKNOWN
Classifier: Development Status :: 4 - Beta
Classifier: Intended Audience :: Developers
Classifier: Programming Language :: Python :: 3.7
Requires-Python: >=3.6.*
Requires-Dist: requests
Requires-Dist: beautifulsoup4
Requires-Dist: six
Requires-Dist: newspaper3k
Requires-Dist: feedparser
Requires-Dist: pandas
Requires-Dist: goose3
